[
    {
        "title": "The Witcher 3: Wild Hunt",
        "developer": "CD Projekt Red",
        "genre": "RPG",
        "published": "2015",
        "cover": "https://upload.wikimedia.org/wikipedia/en/0/0c/Witcher_3_cover_art.jpg"
    },
    {
        "title": "Red Dead Redemption 2",
        "developer": "Rockstar Games",
        "genre": "Action-Adventure",
        "published": "2018",
        "cover": "https://upload.wikimedia.org/wikipedia/en/4/44/Red_Dead_Redemption_II.jpg"
    },
    {
        "title": "Cyberpunk 2077",
        "developer": "CD Projekt Red",
        "genre": "RPG",
        "published": "2020",
        "cover": "https://upload.wikimedia.org/wikipedia/en/9/9f/Cyberpunk_2077_box_art.jpg"
    },
    {
        "title": "The Legend of Zelda: Breath of the Wild",
        "developer": "Nintendo",
        "genre": "Action-Adventure",
        "published": "2017",
        "cover": "https://upload.wikimedia.org/wikipedia/en/c/c6/The_Legend_of_Zelda_Breath_of_the_Wild.jpg"
    },
    {
        "title": "God of War (2018)",
        "developer": "Santa Monica Studio",
        "genre": "Action-Adventure",
        "published": "2018",
        "cover": "https://upload.wikimedia.org/wikipedia/en/a/a7/God_of_War_4_cover.jpg"
    },
    {
        "title": "Horizon Zero Dawn",
        "developer": "Guerrilla Games",
        "genre": "Action RPG",
        "published": "2017",
        "cover": "https://upload.wikimedia.org/wikipedia/en/a/a8/Horizon_Zero_Dawn.jpg"
    },
    {
        "title": "Dark Souls III",
        "developer": "FromSoftware",
        "genre": "Action RPG",
        "published": "2016",
        "cover": "https://upload.wikimedia.org/wikipedia/en/8/85/Dark_Souls_III_cover_art.jpg"
    },
    {
        "title": "Minecraft",
        "developer": "Mojang",
        "genre": "Sandbox, Survival",
        "published": "2011",
        "cover": "https://upload.wikimedia.org/wikipedia/en/5/51/Minecraft_cover.png"
    }
]
